mouadsadik_picsou/__init__.py
mouadsadik_picsou/picsou.py
mouadsadik_picsou-0.1.0.dist-info/METADATA
mouadsadik_picsou-0.1.0.dist-info/WHEEL
mouadsadik_picsou-0.1.0.dist-info/RECORD
