Metadata-Version: 2.1
Name: mouadsadik-picsou
Version: 0.1.0
Summary: 
Author: sadistic001
Author-email: mouad.sadik@ig2i.centralelillle.fr
Requires-Python: >=3.12,<4.0
Classifier: Programming Language :: Python :: 3
Classifier: Programming Language :: Python :: 3.12
Requires-Dist: coverage (>=7.4.1,<8.0.0)
